{
  "tasks": [
    {
      "name": "WIGOS-118400 - Salones - ERP Luckia - Pago apuestas - Kiosco (501) registra 0 aunque hay movimientos que deberían mostrarse",
      "description": "",
      "branch": "",
      "estimated": "",
      "completed": true,
      "createdAt": "2025-11-20T13:47:41.515Z",
      "date": "2025-11-17",
      "hours": 6,
      "id": 15
    },
    {
      "name": "WIGOS-118415 - Salones - ERP Luckia - Pagos online - Kiosco (502) y Deposito online - Kiosco (503) los valores se encuentran cruzados",
      "description": "https://winsytemsintl.atlassian.net/browse/WIGOS-118415",
      "branch": "",
      "estimated": "",
      "completed": true,
      "createdAt": "2025-11-20T13:48:12.354Z",
      "date": "2025-11-17",
      "hours": 2,
      "id": 16
    },
    {
      "name": "WIGOS-117972 - Salones - ERP Luckia - Atributos de concepto de entrada (300) no se están registrando en el fichero",
      "description": "",
      "branch": "",
      "estimated": "",
      "completed": true,
      "createdAt": "2025-11-20T13:48:35.576Z",
      "date": "2025-11-17",
      "hours": 0.5,
      "id": 17
    },
    {
      "name": "WIGOS-117972 - Salones - ERP Luckia - Atributos de concepto de entrada (300) no se están registrando en el fichero",
      "description": "",
      "branch": "",
      "estimated": "",
      "completed": true,
      "createdAt": "2025-11-20T13:49:27.504Z",
      "date": "2025-11-18",
      "hours": 6,
      "id": 18
    },
    {
      "name": "WIGOS-118481 - Refinement - WIGOS-118194 Luckia - ERP data integration v1.3",
      "description": "",
      "branch": "",
      "estimated": "",
      "completed": true,
      "createdAt": "2025-11-20T13:49:47.748Z",
      "date": "2025-11-18",
      "hours": 0.25,
      "id": 19
    },
    {
      "name": "WIGOS-118488 - Refinement - WIGOS-109375 Luckia - ERP data integration v4 (foreign currencies)",
      "description": "",
      "branch": "",
      "estimated": "",
      "completed": true,
      "createdAt": "2025-11-20T13:50:05.770Z",
      "date": "2025-11-18",
      "hours": 0.25,
      "id": 20
    },
    {
      "name": "WIGOS-118159 - ERP Luckia - Pasivo Inicial (604) Valor mal calculado Pasivo Inicial",
      "description": "",
      "branch": "",
      "estimated": "",
      "completed": true,
      "createdAt": "2025-11-20T13:50:33.415Z",
      "date": "2025-11-18",
      "hours": 1,
      "id": 21
    },
    {
      "name": "WIGOS-117823 - ERP Luckia - Pasivo Final (605) Campo mal calculado Pasivo Final",
      "description": "",
      "branch": "",
      "estimated": "",
      "completed": true,
      "createdAt": "2025-11-20T13:50:50.179Z",
      "date": "2025-11-18",
      "hours": 1,
      "id": 22
    },
    {
      "name": "WIGOS-118546 - Salones - ERP Luckia - Errores detectados en el Laboratorio del cliente. Problemas de regionalización de fechas.",
      "description": "",
      "branch": "",
      "estimated": "",
      "completed": true,
      "createdAt": "2025-11-20T13:51:29.689Z",
      "date": "2025-11-19",
      "hours": 8.5,
      "id": 23
    },
    {
      "name": "WIGOS-118114 - Salones - ERP Luckia - (245) Tickets caducados no se suman para el fichero csv",
      "description": "",
      "branch": "feature/sln2/wigos-118114_salones_erp_luckia_245_tickets_caducados_no_se_suman_para_el_fichero_csv",
      "estimated": "",
      "completed": true,
      "createdAt": "2025-11-20T13:52:04.356Z",
      "date": "2025-11-20",
      "hours": 8.5,
      "id": 24,
      "repositoryId": 1
    },
    {
      "name": "WIGOS-117823 - ERP Luckia - Pasivo Final (605) Campo mal calculado Pasivo Final",
      "description": "",
      "branch": "",
      "estimated": "",
      "completed": true,
      "createdAt": "2025-11-20T14:12:33.142Z",
      "date": "2025-11-10",
      "hours": 6,
      "id": 25
    },
    {
      "name": "WIGOS-117972 - Salones - ERP Luckia - Atributos de concepto de entrada (300) no se están registrando en el fichero",
      "description": "",
      "branch": "",
      "estimated": "",
      "completed": true,
      "createdAt": "2025-11-20T14:12:54.647Z",
      "date": "2025-11-10",
      "hours": 2,
      "id": 26
    },
    {
      "name": "WIGOS-118208 - Refinement - WIGOS-111228 GORGE -> WigosOne integration (Orenes) v1.0 | Manufacturer and Model maintenance",
      "description": "",
      "branch": "",
      "estimated": "",
      "completed": true,
      "createdAt": "2025-11-20T14:13:13.103Z",
      "date": "2025-11-10",
      "hours": 0.5,
      "id": 27
    },
    {
      "name": "WIGOS-117972 - Salones - ERP Luckia - Atributos de concepto de entrada (300) no se están registrando en el fichero",
      "description": "",
      "branch": "",
      "estimated": "",
      "completed": true,
      "createdAt": "2025-11-20T14:13:30.638Z",
      "date": "2025-11-11",
      "hours": 1.5,
      "id": 28
    },
    {
      "name": "WIGOS-117971 - Salones - ERP Luckia - Atributos de concepto de salida (400) contiene valores incorrectos",
      "description": "",
      "branch": "",
      "estimated": "",
      "completed": true,
      "createdAt": "2025-11-20T14:13:49.816Z",
      "date": "2025-11-11",
      "hours": 1.5,
      "id": 29
    },
    {
      "name": "WIGOS-118221 - Salones - ERP Integration V1 - En el archivo csv se ha generado con el cambio de día natural en lugar de tomar la fecha de \"GamingHallExtractionWorkingDayStart\" definida para los salones",
      "description": "",
      "branch": "",
      "estimated": "",
      "completed": true,
      "createdAt": "2025-11-20T14:14:17.388Z",
      "date": "2025-11-11",
      "hours": 5.5,
      "id": 30
    },
    {
      "name": "WIGOS-118221 - Salones - ERP Integration V1 - En el archivo csv se ha generado con el cambio de día natural en lugar de tomar la fecha de \"GamingHallExtractionWorkingDayStart\" definida para los salones",
      "description": "",
      "branch": "",
      "estimated": "",
      "completed": true,
      "createdAt": "2025-11-20T14:15:04.963Z",
      "date": "2025-11-12",
      "hours": 4,
      "id": 31
    },
    {
      "name": "WIGOS-117972 - Salones - ERP Luckia - Atributos de concepto de entrada (300) no se están registrando en el fichero",
      "description": "",
      "branch": "",
      "estimated": "",
      "completed": true,
      "createdAt": "2025-11-20T14:15:28.018Z",
      "date": "2025-11-12",
      "hours": 4.5,
      "id": 32
    },
    {
      "name": "WIGOS-118159 - ERP Luckia - Pasivo Inicial (604) Valor mal calculado Pasivo Inicial",
      "description": "",
      "branch": "feature/sln2/wigos-118159_erp_luckia_pasivo_inicial_604_valor_mal_calculado_pasivo_inicial",
      "estimated": "",
      "completed": true,
      "createdAt": "2025-11-20T14:15:48.528Z",
      "date": "2025-11-13",
      "hours": 3,
      "id": 33
    },
    {
      "name": "WIGOS-117711 - Salones - Reporte de efectivo de sala - con WigosCollect - se están restando los movimientos de reposiciones y retiros de kiosco al realizar las recaudaciones de máquinas con la app, pero todavía no se ha cerrado la sesión de caja del recaudador",
      "description": "",
      "branch": "feature/sln2/WIGOS-117711_Reporte_de_efectivo_de_sala_reposiciones_retiros_restados_sin_cerrar_sesion_recaudador",
      "estimated": "",
      "completed": true,
      "createdAt": "2025-11-20T14:16:03.667Z",
      "date": "2025-11-13",
      "hours": 5.5,
      "id": 34
    },
    {
      "name": "WIGOS-117711 - Salones - Reporte de efectivo de sala - con WigosCollect - se están restando los movimientos de reposiciones y retiros de kiosco al realizar las recaudaciones de máquinas con la app, pero todavía no se ha cerrado la sesión de caja del recaudador",
      "description": "",
      "branch": "feature/sln2/WIGOS-117711_Reporte_de_efectivo_de_sala_reposiciones_retiros_restados_sin_cerrar_sesion_recaudador",
      "estimated": "",
      "completed": true,
      "createdAt": "2025-11-20T14:16:36.567Z",
      "date": "2025-11-14",
      "hours": 6,
      "id": 35
    },
    {
      "name": "WIGOS-117758 - ERP Luckia - Recargas Cashless (210) Campo mal calculado para recargas cashless",
      "description": "WIGOS-117758 - ERP Luckia - Recargas Cashless (210) Campo mal calculado para recargas cashless",
      "branch": "",
      "estimated": "",
      "completed": true,
      "createdAt": "2025-11-20T17:10:46.380Z",
      "date": "2025-11-03",
      "hours": 2,
      "id": 36
    },
    {
      "name": "WIGOS-117776 - ERP Luckia - Reintegros Cashless (211) Campo mal calculado para reintegros cashless",
      "description": "WIGOS-117776 - ERP Luckia - Reintegros Cashless (211) Campo mal calculado para reintegros cashless",
      "branch": "",
      "estimated": "",
      "completed": true,
      "createdAt": "2025-11-20T17:11:06.017Z",
      "date": "2025-11-03",
      "hours": 2,
      "id": 37
    },
    {
      "name": "WIGOS-117821 - ERP Luckia - Saldo final (tarjetas) (603) Linea de la operación no se registra en el fichero csv",
      "description": "WIGOS-117821 - ERP Luckia - Saldo final (tarjetas) (603) Linea de la operación no se registra en el fichero csv",
      "branch": "",
      "estimated": "",
      "completed": true,
      "createdAt": "2025-11-20T17:11:22.749Z",
      "date": "2025-11-03",
      "hours": 2,
      "id": 38
    },
    {
      "name": "WIGOS-117823 - ERP Luckia - Pasivo Final (605) Campo mal calculado Pasivo Final",
      "description": "WIGOS-117823 - ERP Luckia - Pasivo Final (605) Campo mal calculado Pasivo Final",
      "branch": "",
      "estimated": "",
      "completed": true,
      "createdAt": "2025-11-20T17:11:47.124Z",
      "date": "2025-11-03",
      "hours": 0.5,
      "id": 39
    },
    {
      "name": "WIGOS-117822 - ERP Luckia - TITO IN Redimible (242) Campo mal calculado Tito In Redimible en máquina",
      "description": "WIGOS-117822 - ERP Luckia - TITO IN Redimible (242) Campo mal calculado Tito In Redimible en máquina",
      "branch": "",
      "estimated": "",
      "completed": true,
      "createdAt": "2025-11-20T17:12:08.597Z",
      "date": "2025-11-03",
      "hours": 0.5,
      "id": 40
    },
    {
      "name": "WIGOS-97950  - Rep. máquina | Creación ticket en Cajero con LPS",
      "description": "WIGOS-97950  - Rep. máquina | Creación ticket en Cajero con LPS",
      "branch": "",
      "estimated": "",
      "completed": true,
      "createdAt": "2025-11-20T17:12:28.427Z",
      "date": "2025-11-03",
      "hours": 1.5,
      "id": 41
    },
    {
      "name": "WIGOS-97950  - Rep. máquina | Creación ticket en Cajero con LPS",
      "description": "WIGOS-97950  - Rep. máquina | Creación ticket en Cajero con LPS",
      "branch": "",
      "estimated": "",
      "completed": true,
      "createdAt": "2025-11-20T17:12:47.380Z",
      "date": "2025-11-04",
      "hours": 1.5,
      "id": 42
    },
    {
      "name": "WIGOS-117798 - Integración ERP 1.2 | Conceptos (columna text)",
      "description": "WIGOS-117798 - Integración ERP 1.2 | Conceptos (columna text)",
      "branch": "",
      "estimated": "",
      "completed": true,
      "createdAt": "2025-11-20T17:13:38.125Z",
      "date": "2025-11-04",
      "hours": 2,
      "id": 43
    },
    {
      "name": "WIGOS-117885 - Integración ERP 1.2 | Caja (líneas a cero)",
      "description": "WIGOS-117885 - Integración ERP 1.2 | Caja (líneas a cero)",
      "branch": "",
      "estimated": "",
      "completed": true,
      "createdAt": "2025-11-20T17:14:02.575Z",
      "date": "2025-11-04",
      "hours": 5,
      "id": 44
    },
    {
      "name": "WIGOS-117885 - Integración ERP 1.2 | Caja (líneas a cero)",
      "description": "WIGOS-117885 - Integración ERP 1.2 | Caja (líneas a cero)",
      "branch": "",
      "estimated": "",
      "completed": true,
      "createdAt": "2025-11-20T17:14:26.785Z",
      "date": "2025-11-05",
      "hours": 1.5,
      "id": 45
    },
    {
      "name": "WIGOS-117894 - Integración ERP 1.2 | TITO (anular pagado)",
      "description": "WIGOS-117894 - Integración ERP 1.2 | TITO (anular pagado)",
      "branch": "",
      "estimated": "",
      "completed": true,
      "createdAt": "2025-11-20T17:14:42.251Z",
      "date": "2025-11-05",
      "hours": 1.5,
      "id": 46
    },
    {
      "name": "WIGOS-117971 - Salones - ERP Luckia - Atributos de concepto contiene valores incorrectos",
      "description": "WIGOS-117971 - Salones - ERP Luckia - Atributos de concepto contiene valores incorrectos",
      "branch": "",
      "estimated": "",
      "completed": true,
      "createdAt": "2025-11-20T17:15:04.280Z",
      "date": "2025-11-05",
      "hours": 2,
      "id": 47
    },
    {
      "name": "WIGOS-117972 - Salones - ERP Luckia - Atributos de concepto de entrada (300) no se están registrando en el fichero",
      "description": "WIGOS-117972 - Salones - ERP Luckia - Atributos de concepto de entrada (300) no se están registrando en el fichero",
      "branch": "",
      "estimated": "",
      "completed": true,
      "createdAt": "2025-11-20T17:15:25.280Z",
      "date": "2025-11-05",
      "hours": 1,
      "id": 48
    },
    {
      "name": "WIGOS-117758 - ERP Luckia - Recargas Cashless (210) Campo mal calculado para recargas cashless",
      "description": "WIGOS-117758 - ERP Luckia - Recargas Cashless (210) Campo mal calculado para recargas cashless",
      "branch": "",
      "estimated": "",
      "completed": true,
      "createdAt": "2025-11-20T17:15:38.551Z",
      "date": "2025-11-05",
      "hours": 1.5,
      "id": 49
    },
    {
      "name": "WIGOS-117776 - ERP Luckia - Reintegros Cashless (211) Campo mal calculado para reintegros cashless",
      "description": "WIGOS-117776 - ERP Luckia - Reintegros Cashless (211) Campo mal calculado para reintegros cashless",
      "branch": "",
      "estimated": "",
      "completed": true,
      "createdAt": "2025-11-20T17:15:51.135Z",
      "date": "2025-11-05",
      "hours": 1,
      "id": 50
    },
    {
      "name": "WIGOS-117644 - ERP Luckia - Tickets (243) Campo mal calculado para tickets out de máquina",
      "description": "WIGOS-117644 - ERP Luckia - Tickets (243) Campo mal calculado para tickets out de máquina",
      "branch": "",
      "estimated": "",
      "completed": true,
      "createdAt": "2025-11-20T17:16:10.272Z",
      "date": "2025-11-06",
      "hours": 3,
      "id": 51
    },
    {
      "name": "WIGOS-117822 - ERP Luckia - TITO IN Redimible (242) Campo mal calculado Tito In Redimible en máquina",
      "description": "WIGOS-117822 - ERP Luckia - TITO IN Redimible (242) Campo mal calculado Tito In Redimible en máquina",
      "branch": "",
      "estimated": "",
      "completed": true,
      "createdAt": "2025-11-20T17:16:22.489Z",
      "date": "2025-11-06",
      "hours": 2,
      "id": 52
    },
    {
      "name": "WIGOS-118114 - Salones - ERP Luckia - (245) Tickets caducados no se suman para el fichero csv",
      "description": "WIGOS-118114 - Salones - ERP Luckia - (245) Tickets caducados no se suman para el fichero csv",
      "branch": "",
      "estimated": "",
      "completed": true,
      "createdAt": "2025-11-20T17:16:34.167Z",
      "date": "2025-11-06",
      "hours": 2,
      "id": 53
    },
    {
      "name": "WIGOS-117913 - Project Plan - WIGOS-117797 Luckia - ERP data integration v1.2",
      "description": "WIGOS-117913 - Project Plan - WIGOS-117797 Luckia - ERP data integration v1.2",
      "branch": "",
      "estimated": "",
      "completed": true,
      "createdAt": "2025-11-20T17:16:48.745Z",
      "date": "2025-11-06",
      "hours": 1.5,
      "id": 54
    },
    {
      "name": "WIGOS-117823 - ERP Luckia - Pasivo Final (605) Campo mal calculado Pasivo Final",
      "description": "WIGOS-117823 - ERP Luckia - Pasivo Final (605) Campo mal calculado Pasivo Final",
      "branch": "",
      "estimated": "",
      "completed": true,
      "createdAt": "2025-11-20T17:17:18.019Z",
      "date": "2025-11-07",
      "hours": 1.5,
      "id": 55
    },
    {
      "name": "SOPORTE DANI BLOQUEOS EN ORENES CLIENTE CON LA v36",
      "description": "SOPORTE DANI BLOQUEOS EN ORENES CLIENTE CON LA v36\n\nEsta tarea no tiene ticket asociado!!",
      "branch": "",
      "estimated": "",
      "completed": true,
      "createdAt": "2025-11-20T17:17:51.891Z",
      "date": "2025-11-07",
      "hours": 4.5,
      "id": 56
    },
    {
      "name": "WIGOS-118382 - Salones - Reporte de efectivo de sala - con WigosCollect - los datos de reposiciones y retiros de kiosco se están \"multiplicando\" en el dato de \"Tickets pendientes de reponer\" por cada operación de este tipo realizada con la app",
      "description": "Salones - \n  Reporte de efectivo de sala -\n     WigosCollect - \n        Los datos de reposiciones y retiros de kiosco se están \"multiplicando\" en el dato de \"Tickets pendientes de reponer\" por cada operación de este tipo realizada con la app",
      "branch": "master",
      "estimated": "",
      "completed": true,
      "createdAt": "2025-11-21T09:29:49.425Z",
      "date": "2025-11-21",
      "hours": 6,
      "itemId": "WIGOS-118382",
      "repositoryId": 1,
      "id": 59
    },
    {
      "name": "WIGOS-117711 - Salones - Reporte de efectivo de sala - con WigosCollect - se están restando los movimientos de reposiciones y retiros de kiosco al realizar las recaudaciones de máquinas con la app, pero todavía no se ha cerrado la sesión de caja del recaudador",
      "description": "Salones - Reporte de efectivo de sala - con WigosCollect - se están restando los movimientos de reposiciones y retiros de kiosco al realizar las recaudaciones de máquinas con la app, pero todavía no se ha cerrado la sesión de caja del recaudador",
      "branch": "master",
      "completed": true,
      "createdAt": "2025-11-21T13:25:54.612Z",
      "date": "2025-10-31",
      "hours": 6,
      "itemId": "WIGOS-117711",
      "repositoryId": "2",
      "id": 63
    },
    {
      "name": "WIGOS-117711 - Salones - Reporte de efectivo de sala - con WigosCollect - se están restando los movimientos de reposiciones y retiros de kiosco al realizar las recaudaciones de máquinas con la app, pero todavía no se ha cerrado la sesión de caja del recaudador",
      "description": "Salones - Reporte de efectivo de sala - con WigosCollect - se están restando los movimientos de reposiciones y retiros de kiosco al realizar las recaudaciones de máquinas con la app, pero todavía no se ha cerrado la sesión de caja del recaudador",
      "branch": "master",
      "completed": true,
      "createdAt": "2025-11-21T13:26:45.980Z",
      "date": "2025-10-30",
      "hours": 7.5,
      "itemId": "WIGOS-117711",
      "repositoryId": "2",
      "id": 64
    },
    {
      "name": "WIGOS-116531 - Cambios en PerformanceLog Viewer",
      "description": "Cambios en PerformanceLog Viewer",
      "branch": "master",
      "completed": true,
      "createdAt": "2025-11-21T13:28:57.517Z",
      "date": "2025-10-30",
      "hours": 1,
      "itemId": "WIGOS-116531",
      "repositoryId": "5",
      "id": 65
    },
    {
      "name": "WIGOS-117644 - ERP Luckia - Tickets (243) Campo mal calculado para tickets out de máquina",
      "description": "ERP Luckia - Tickets (243) Campo mal calculado para tickets out de máquina",
      "branch": "master",
      "completed": true,
      "createdAt": "2025-11-21T13:29:35.458Z",
      "date": "2025-10-29",
      "hours": 4.5,
      "itemId": "WIGOS-117644",
      "repositoryId": "1",
      "id": 66
    },
    {
      "name": "WIGOS-97950  - Rep. máquina | Creación ticket en Cajero con LPS",
      "description": "Rep. máquina | Creación ticket en Cajero con LPS",
      "branch": "master",
      "completed": true,
      "createdAt": "2025-11-21T13:30:42.706Z",
      "date": "2025-10-29",
      "hours": 4,
      "itemId": "WIGOS-97950",
      "repositoryId": "2",
      "id": 67
    },
    {
      "name": "WIGOS-97950  - Rep. máquina | Creación ticket en Cajero con LPS",
      "description": "Rep. máquina | Creación ticket en Cajero con LPS",
      "branch": "master",
      "completed": true,
      "createdAt": "2025-11-21T13:31:22.663Z",
      "date": "2025-10-28",
      "hours": 5.5,
      "itemId": "WIGOS-97950",
      "repositoryId": "2",
      "id": 68
    },
    {
      "name": "WIGOS-117530 - Salones LPS - Recaudación - Edición manual de contadores -- Hay máquinas con el check de \"Contadores editables en recaudación\" que no lo tienen en cuenta al recaudar y viceversa",
      "description": "Salones LPS - Recaudación - Edición manual de contadores -- Hay máquinas con el check de \"Contadores editables en recaudación\" que no lo tienen en cuenta al recaudar y viceversa",
      "branch": "master",
      "completed": true,
      "createdAt": "2025-11-21T13:32:05.017Z",
      "date": "2025-10-28",
      "hours": 2,
      "itemId": "WIGOS-117530",
      "repositoryId": "2",
      "id": 69
    },
    {
      "name": "WIGOS-116531 - Cambios en PerformanceLog Viewer",
      "description": "Cambios en PerformanceLog Viewer",
      "branch": "master",
      "completed": true,
      "createdAt": "2025-11-21T13:32:33.833Z",
      "date": "2025-10-28",
      "hours": 1,
      "itemId": "WIGOS-116531",
      "repositoryId": "5",
      "id": 70
    },
    {
      "name": "WIGOS-117530 - Salones LPS - Recaudación - Edición manual de contadores -- Hay máquinas con el check de \"Contadores editables en recaudación\" que no lo tienen en cuenta al recaudar y viceversa",
      "description": "Salones LPS - Recaudación - Edición manual de contadores -- Hay máquinas con el check de \"Contadores editables en recaudación\" que no lo tienen en cuenta al recaudar y viceversa",
      "branch": "master",
      "completed": true,
      "createdAt": "2025-11-21T13:33:07.374Z",
      "date": "2025-10-27",
      "hours": 3.5,
      "itemId": "WIGOS-117530",
      "repositoryId": "2",
      "id": 71
    },
    {
      "name": "WIGOS-117475 - Salones LPS - Cajero - Recaudación - Log error -- EXCEPTION: transaction - Invalid connection. Expected LPS database.",
      "description": "Salones LPS - Cajero - Recaudación - Log error -- EXCEPTION: transaction - Invalid connection. Expected LPS database.",
      "branch": "master",
      "completed": true,
      "createdAt": "2025-11-21T13:34:13.192Z",
      "date": "2025-10-27",
      "hours": 3,
      "itemId": "WIGOS-117475",
      "repositoryId": "2",
      "id": 72
    },
    {
      "name": "WIGOS-116531 - Cambios en PerformanceLog Viewer",
      "description": "Cambios en PerformanceLog Viewer",
      "branch": "master",
      "completed": true,
      "createdAt": "2025-11-21T13:34:39.113Z",
      "date": "2025-10-27",
      "hours": 2,
      "itemId": "WIGOS-116531",
      "repositoryId": "5",
      "id": 73
    },
    {
      "name": "WIGOS-118382 - Salones - Reporte de efectivo de sala - con WigosCollect - los datos de reposiciones y retiros de kiosco se están \"multiplicando\" en el dato de \"Tickets pendientes de reponer\" por cada operación de este tipo realizada con la app",
      "description": "Salones \n - Reporte de efectivo de sala con WigosCollect \n  - los datos de reposiciones y retiros de kiosco se están \"multiplicando\" en el dato de \"Tickets pendientes de reponer\" por cada operación de este tipo realizada con la app",
      "branch": "feature/sln2/wigos-118382_salones_reporte_de_efectivo_de_sala_con_wigoscollect_los_datos_de_reposiciones_y_retiros_de_kiosco_se_estan_multiplicando",
      "completed": true,
      "createdAt": "2025-11-21T13:51:09.093Z",
      "date": "2025-11-24",
      "hours": 1,
      "itemId": "WIGOS-118382",
      "repositoryId": "1",
      "id": 74,
      "mergeIn": "master"
    },
    {
      "name": "WIGOS-117972 - Salones - ERP Luckia - Atributos de concepto de entrada (300) no se están registrando en el fichero",
      "description": "Salones \n- ERP Luckia \n- Atributos de concepto de entrada (300) no se están registrando en el fichero",
      "branch": "feature/sln2/wigos-117972_salones_erp_luckia_atributos_de_concepto_de_entrada_300_no_se_estan_registrando_en_el_fichero_nueva_branch",
      "mergeIn": "master",
      "completed": true,
      "createdAt": "2025-12-02T15:07:23.486Z",
      "date": "2025-12-02",
      "hours": 6,
      "itemId": "WIGOS-117972",
      "repositoryId": 1,
      "type": "WIGOS",
      "id": 75
    },
    {
      "name": "WIGOS-118194 - Luckia - ERP data integration v1.3",
      "description": "Luckia - ERP data integration v1.3",
      "branch": "feature/sln2/wigos-118194_luckia_erp_data_integration_v1_3",
      "mergeIn": "master",
      "completed": true,
      "createdAt": "2025-12-02T15:10:24.839Z",
      "date": "2025-12-02",
      "hours": 2.5,
      "itemId": "WIGOS-118194",
      "repositoryId": 1,
      "type": "WIGOS",
      "id": 76
    },
    {
      "name": "WIGOS-118194 - Luckia - ERP data integration v1.3",
      "description": "Épica --> Luckia - ERP data integration v1.3 || US: WIGOS-118196 - Integración ERP 1.3 | Mensaje para Luckia Salones - TITOs Redimibles",
      "branch": "feature/sln2/wigos-118194_luckia_erp_data_integration_v1_3",
      "mergeIn": "master",
      "completed": true,
      "createdAt": "2025-12-02T15:10:24.839Z",
      "date": "2025-12-03",
      "hours": 5,
      "itemId": "WIGOS-118194",
      "repositoryId": 1,
      "type": "WIGOS",
      "id": 77
    },
    {
      "name": "VACACIONES",
      "description": "Navidad",
      "branch": "",
      "mergeIn": "",
      "completed": false,
      "createdAt": "2025-12-03T07:29:21.816Z",
      "date": "2025-12-29",
      "hours": 8,
      "itemId": "TASK-00001",
      "type": "VACACIONES",
      "id": 78
    },
    {
      "name": "VACACIONES",
      "description": "Navidad",
      "branch": "",
      "mergeIn": "",
      "completed": false,
      "createdAt": "2025-12-03T07:40:15.512Z",
      "date": "2025-12-30",
      "hours": 8,
      "itemId": "TASK-00002",
      "type": "VACACIONES",
      "id": 79
    },
    {
      "name": "VACACIONES",
      "description": "Navidad",
      "branch": "",
      "mergeIn": "",
      "completed": false,
      "createdAt": "2025-12-03T07:40:30.502Z",
      "date": "2025-12-31",
      "hours": 8,
      "itemId": "TASK-00003",
      "type": "VACACIONES",
      "id": 80
    },
    {
      "name": "VACACIONES",
      "description": "Navidad",
      "branch": "",
      "mergeIn": "",
      "completed": false,
      "createdAt": "2025-12-03T07:40:50.646Z",
      "date": "2026-01-02",
      "hours": 8,
      "itemId": "TASK-00004",
      "type": "VACACIONES",
      "id": 81
    },
    {
      "name": "VACACIONES",
      "description": "Navidad",
      "branch": "",
      "mergeIn": "",
      "completed": false,
      "createdAt": "2025-12-03T07:41:09.102Z",
      "date": "2026-01-05",
      "hours": 8,
      "itemId": "TASK-00005",
      "type": "VACACIONES",
      "id": 82
    },
    {
      "name": "WIGOS-119159 - Salones - GUI - Reporte simplificado de recaudación - Filtrando por máquina el reporte queda vacío",
      "description": "Salones \n - GUI \n  - Reporte simplificado de recaudación \n   - Filtrando por máquina el reporte queda vacío",
      "branch": "feature/sln2/wigos-119159_salones_gui_reporte_simplificado_de_recaudacion_filtrando_por_maquina_el_reporte_queda_vacio",
      "mergeIn": "hotfix/hotfix-37",
      "completed": true,
      "createdAt": "2025-12-03T08:20:30.138Z",
      "date": "2025-12-03",
      "hours": 4.5,
      "itemId": "WIGOS-119159",
      "repositoryId": 5,
      "type": "WIGOS",
      "id": 83
    },
    {
      "name": "WIGOS-118194 - Luckia - ERP data integration v1.3",
      "description": "<h3><strong>Épica --&gt; Luckia - ERP data integration v1.3</strong></h3><p>US:</p><p class=\"ql-indent-1\">WIGOS-118196 - Integración ERP 1.3 | Mensaje para Luckia Salones - TITOs Redimibles</p><p>NOTAS:</p><p class=\"ql-indent-1\">Queda pendiente sacar release de Sprint. La <strong>ERP Data Integration v1.3 y la ERP Data Integration v4</strong> saldrán juntas de esta branch</p>",
      "branch": "feature/sln2/wigos-118194_luckia_erp_data_integration_v1_3",
      "mergeIn": "master",
      "completed": true,
      "createdAt": "2025-12-02T15:10:24.839Z",
      "date": "2025-12-04",
      "hours": 2.5,
      "itemId": "WIGOS-118194",
      "repositoryId": 1,
      "type": "WIGOS",
      "id": 85
    },
    {
      "name": "WIGOS-109375 - Luckia - ERP data integration v4 (foreign currencies)",
      "description": "WIGOS-109375 - Luckia - ERP data integration v4 (foreign currencies) \n<p>US:</p>\n<p style=\"border:1px blue solid; padding:2px; margin:2px\">WIGOS-109486 - Integración ERP 4 | Mensajes para Luckia | Divisas</p>",
      "branch": "feature/sln2/wigos-109375_luckia_erp_data_integration_v4_foreign_currencies",
      "mergeIn": "master",
      "completed": true,
      "createdAt": "2025-12-04T11:52:47.721Z",
      "date": "2025-12-04",
      "hours": 6,
      "itemId": "WIGOS-109375",
      "repositoryId": 1,
      "type": "WIGOS",
      "id": 86
    },
    {
      "name": "WIGOS-109375 - Luckia - ERP data integration v4 (foreign currencies)",
      "description": "<p>WIGOS-109375 - Luckia - ERP data integration v4 (foreign currencies)</p><p>US:</p><ul><li><strong>WIGOS-109486 - Integración ERP 4 | Mensajes para Luckia | Divisas</strong></li><li class=\"ql-indent-1\">SAP Code 216 --&gt; Hecho</li><li class=\"ql-indent-1\">SAP Code 217 --&gt; Hecho</li><li class=\"ql-indent-1\">SAP Code 218 --&gt; Hecho</li><li class=\"ql-indent-1\">SAP Code 219 --&gt; Hecho</li><li><strong>WIGOS-109487 - Integración ERP 4 | Mensajes para Luckia | Caja (divisas)</strong></li><li class=\"ql-indent-1\">SAP Code 600 --&gt; Fix para filtrar solo por la divisa local 'EUR'.</li><li class=\"ql-indent-1\">SAP Code 601 --&gt; Hecho</li><li><strong>WIGOS-109508 - Integración ERP 4 | Mensajes para Luckia | Conceptos (divisas)</strong></li><li class=\"ql-indent-1\"><strong>﻿SAP Code 300 --&gt; Modificado</strong></li><li class=\"ql-indent-1\"><strong>SAP Code 400 --&gt; Modificado</strong></li></ul><p><br></p><p><strong>VERSION DE SPRINT LIBERADA!</strong></p>",
      "branch": "feature/sln2/wigos-109375_luckia_erp_data_integration_v4_foreign_currencies",
      "mergeIn": "master",
      "completed": true,
      "createdAt": "2025-12-04T11:52:47.721Z",
      "date": "2025-12-05",
      "hours": 6,
      "itemId": "WIGOS-109375",
      "repositoryId": 1,
      "type": "WIGOS",
      "id": 87
    },
    {
      "name": "WIGOS-119183 - Salones - GUI - Reporte de beneficio por máquina y fecha - No muestra datos al filtrar por máquina",
      "description": "<p>Salones - GUI - Reporte de beneficio por máquina y fecha - No muestra datos al filtrar por máquina</p><p><br></p><p>HECHO EN hotfix/hotfix_37 y en master</p>",
      "branch": "feature/sln2/wigos-119183_salones_gui_reporte_de_beneficio_por_maquina_y_fecha_no_muestra_datos_al_filtrar_por_maquina",
      "mergeIn": "hotfix/hotfix-37",
      "completed": true,
      "createdAt": "2025-12-09T08:27:13.677Z",
      "date": "2025-12-09",
      "hours": 4.5,
      "itemId": "WIGOS-119183",
      "repositoryId": 5,
      "type": "WIGOS",
      "id": 88
    },
    {
      "name": "WIGOS-117972 - Salones - ERP Luckia - Atributos de concepto de entrada (300) no se están registrando en el fichero",
      "description": "<p>Salones - ERP Luckia - Atributos de concepto de entrada (300) no se están registrando en el fichero. Revisión en el entorno 498 y 798 de QA con Javi</p><p><br></p><p><strong style=\"color: rgb(169, 171, 175); background-color: transparent;\">WIGOS-117971</strong><strong> </strong>- Salones - ERP Luckia - Atributos de concepto de salida (400) contiene valores incorrectos</p>",
      "branch": "feature/sln2/wigos-117972_salones_erp_luckia_atributos_de_concepto_de_entrada_300_no_se_estan_registrando_en_el_fichero_y_sap_code_400",
      "mergeIn": "master",
      "completed": true,
      "createdAt": "2025-12-02T15:07:23.486Z",
      "date": "2025-12-09",
      "hours": 4,
      "itemId": "WIGOS-117972",
      "repositoryId": 1,
      "type": "WIGOS",
      "id": 89
    },
    {
      "name": "Presentación aplicación PerformanceLogger",
      "description": "<p>Presentación a Joaquín de la versión inicial de la aplicación.</p><p>Sala Buenos Aires.</p>",
      "branch": "",
      "mergeIn": "",
      "completed": true,
      "createdAt": "2025-12-10T08:51:04.772Z",
      "date": "2025-12-10",
      "hours": 0.5,
      "itemId": "TASK-00001",
      "type": "OTROS",
      "id": 91
    },
    {
      "name": "WIGOS-119562   Salones - Cajero - Recaudación de máquinas - la finalización de la recaudación queda congelada. No finaliza ni devuelve error en pantalla. - Error en el log: Error:Error in AOP aspect (OnExit): 'count' must be non-negative.",
      "description": "<p>Salones - Cajero - Recaudación de máquinas - la finalización de la recaudación queda congelada. No finaliza ni devuelve error en pantalla. - Error en el log: Error:Error in AOP aspect (OnExit): 'count' must be non-negative.</p>",
      "branch": "feature/sln2/wigos-119562_salones_cajero_recaudacion_de_maquinas_la_finalizacion_de_la_recaudacion_queda_congelada_no_finaliza_ni_devuelve_error_en_pantalla_error_en_el_log_error_error_in_aop_aspect_onexit_count_must_be_non_negative",
      "mergeIn": "hotfix/hotfix-37",
      "completed": true,
      "createdAt": "2025-12-10T11:22:31.334Z",
      "date": "2025-12-10",
      "hours": 7,
      "itemId": "WIGOS-119562",
      "repositoryId": 2,
      "type": "WIGOS",
      "id": 92
    }
  ],
  "user": [
    {
      "name": "Oscar Mas",
      "email": "o.mas@winsysgroup.com",
      "role": "Senior .NET Developer",
      "theme": "light",
      "language": "en",
      "id": 1
    },
    {
      "name": "John Doe",
      "email": "john@example.com",
      "role": "Developer",
      "theme": "light",
      "language": "en",
      "id": 2
    },
    {
      "name": "John Doe",
      "email": "john@example.com",
      "role": "Developer",
      "theme": "light",
      "language": "en",
      "id": 3
    },
    {
      "name": "John Doe",
      "email": "john@example.com",
      "role": "Developer",
      "theme": "light",
      "language": "en",
      "id": 4
    }
  ]
}
